pacifica_cartd-0.7.0-py3.8-nspkg.pth
pacifica/cartd/__init__.py
pacifica/cartd/__main__.py
pacifica/cartd/archive_requests.py
pacifica/cartd/config.py
pacifica/cartd/fixit.py
pacifica/cartd/globals.py
pacifica/cartd/orm.py
pacifica/cartd/rest.py
pacifica/cartd/tasks.py
pacifica/cartd/utils.py
pacifica/cartd/wsgi.py
pacifica_cartd-0.7.0.dist-info/LICENSE
pacifica_cartd-0.7.0.dist-info/METADATA
pacifica_cartd-0.7.0.dist-info/WHEEL
pacifica_cartd-0.7.0.dist-info/entry_points.txt
pacifica_cartd-0.7.0.dist-info/namespace_packages.txt
pacifica_cartd-0.7.0.dist-info/top_level.txt
pacifica_cartd-0.7.0.dist-info/RECORD
