Metadata-Version: 2.1
Name: pacifica-cartd
Version: 0.7.0
Summary: Pacifica Cartd
Home-page: https://github.com/pacifica/pacifica-cartd/
Author: David Brown
Author-email: dmlb2000@gmail.com
License: UNKNOWN
Platform: UNKNOWN
Requires-Dist: celery
Requires-Dist: cherrypy
Requires-Dist: jsonschema
Requires-Dist: pacifica-namespace
Requires-Dist: peewee (>2)
Requires-Dist: psutil
Requires-Dist: pyyaml
Requires-Dist: requests
Requires-Dist: setuptools
Requires-Dist: tqdm
